MANIFEST.in
README.rst
setup.py
bin/robotreviewer
robotreviewer/.gitignore
robotreviewer/.gitmodules
robotreviewer/README.md
robotreviewer/__init__.py
robotreviewer/__init__.pyc
robotreviewer/biasrobot.py
robotreviewer/biasrobot.pyc
robotreviewer/classifier.py
robotreviewer/classifier.pyc
robotreviewer/cmd_line.py
robotreviewer/cmd_line.pyc
robotreviewer/robot.py
robotreviewer/robot.pyc
robotreviewer/vectorizer.py
robotreviewer/vectorizer.pyc
robotreviewer.egg-info/PKG-INFO
robotreviewer.egg-info/SOURCES.txt
robotreviewer.egg-info/dependency_links.txt
robotreviewer.egg-info/entry_points.txt
robotreviewer.egg-info/not-zip-safe
robotreviewer.egg-info/requires.txt
robotreviewer.egg-info/top_level.txt