Metadata-Version: 1.0
Name: robotreviewer
Version: 0.0.4
Summary: Automatic extraction of data from clinical trial reports
Home-page: https://github.com/ijmarshall/robotreviewer
Author: Edward Banner
Author-email: edward.banner@gmail.com
License: GPL
Platform: UNKNOWN
